starlette_plugins.py
starlette_plugins-0.0.7.dist-info/LICENSE
starlette_plugins-0.0.7.dist-info/METADATA
starlette_plugins-0.0.7.dist-info/WHEEL
starlette_plugins-0.0.7.dist-info/top_level.txt
starlette_plugins-0.0.7.dist-info/RECORD
