Metadata-Version: 2.1
Name: starlette-plugins
Version: 0.0.7
Summary: Create Starlette Plugins easier
Home-page: UNKNOWN
Author: Kirill Klenov
Author-email: horneds@gmail.com
License: MIT
Keywords: starlette plugins
Platform: UNKNOWN
Classifier: Development Status :: 5 - Production/Stable
Classifier: Intended Audience :: Developers
Classifier: License :: OSI Approved :: MIT License
Classifier: Topic :: Software Development :: Libraries
Classifier: Programming Language :: Python :: 3.7
Classifier: Programming Language :: Python :: 3.8
